[
  {"word": "as", "pos": "CONJ", "marathi": "अॅज"},
  {"word": "I", "pos": "PRON", "marathi": "आय"},
  {"word": "his", "pos": "PRON", "marathi": "हिज़"},
  {"word": "that", "pos": "PRON", "marathi": "दॅट"},
  {"word": "he", "pos": "PRON", "marathi": "ही"},
  {"word": "was", "pos": "V", "marathi": "वॉज"},
  {"word": "for", "pos": "PREP", "marathi": "फॉर"},
  {"word": "on", "pos": "PREP", "marathi": "ऑन"},
  {"word": "are", "pos": "V", "marathi": "आर"},
  {"word": "with", "pos": "PREP", "marathi": "विथ"},
  {"word": "they", "pos": "PRON", "marathi": "दे"},
  {"word": "be", "pos": "V", "marathi": "बी"},
  {"word": "at", "pos": "PREP", "marathi": "ऍट"},
  {"word": "one", "pos": "NUM", "marathi": "वन"},
  {"word": "have", "pos": "V", "marathi": "हॅव"},
  {"word": "this", "pos": "PRON", "marathi": "दिस"},
  {"word": "from", "pos": "PREP", "marathi": "फ्रॉम"},
  {"word": "by", "pos": "PREP", "marathi": "बाय"},
  {"word": "hot", "pos": "ADJ", "marathi": "हॉट"},
  {"word": "word", "pos": "N", "marathi": "वर्ड"},
  {"word": "but", "pos": "CONJ", "marathi": "बट"},
  {"word": "what", "pos": "PRON", "marathi": "वॉट"},
  {"word": "some", "pos": "DET", "marathi": "सम"},
  {"word": "is", "pos": "V", "marathi": "इज"},
  {"word": "it", "pos": "PRON", "marathi": "इट"},
  {"word": "you", "pos": "PRON", "marathi": "यू"},
  {"word": "or", "pos": "CONJ", "marathi": "ऑर"},
  {"word": "had", "pos": "V", "marathi": "हॅड"},
  {"word": "the", "pos": "ART", "marathi": "दॅ"},
  {"word": "of", "pos": "PREP", "marathi": "ऑव"},
  {"word": "to", "pos": "PREP", "marathi": "टू"},
  {"word": "and", "pos": "CONJ", "marathi": "ऍंड"},
  {"word": "a", "pos": "ART", "marathi": "ए"},
  {"word": "in", "pos": "PREP", "marathi": "इन"},
  {"word": "we", "pos": "PRON", "marathi": "वी"},
  {"word": "can", "pos": "MODAL", "marathi": "कॅन"},
  {"word": "out", "pos": "PREP", "marathi": "आऊट"},
  {"word": "other", "pos": "ADJ", "marathi": "अदर"},
  {"word": "were", "pos": "V", "marathi": "वेअर"},
  {"word": "which", "pos": "PRON", "marathi": "विच"},
  {"word": "do", "pos": "V", "marathi": "डू"},
  {"word": "their", "pos": "PRON", "marathi": "देअर"},
  {"word": "time", "pos": "N", "marathi": "टाईम"},
  {"word": "if", "pos": "CONJ", "marathi": "इफ"},
  {"word": "will", "pos": "MODAL", "marathi": "विल"},
  {"word": "how", "pos": "ADV", "marathi": "हाउ"},
  {"word": "said", "pos": "V", "marathi": "सेड"},
  {"word": "an", "pos": "ART", "marathi": "ऍन"},
  {"word": "each", "pos": "DET", "marathi": "ईच"},
  {"word": "tell", "pos": "V", "marathi": "टेल"},
  {"word": "does", "pos": "V", "marathi": "डज"},
  {"word": "set", "pos": "V", "marathi": "सेट"},
  {"word": "three", "pos": "NUM", "marathi": "थ्री"},
  {"word": "want", "pos": "V", "marathi": "वॉंट"},
  {"word": "air", "pos": "N", "marathi": "एअर"},
  {"word": "well", "pos": "ADV", "marathi": "वेल"},
  {"word": "also", "pos": "ADV", "marathi": "ऑल्सो"},
  {"word": "play", "pos": "V", "marathi": "प्ले"},
  {"word": "small", "pos": "ADJ", "marathi": "स्मॉल"},
  {"word": "end", "pos": "N", "marathi": "एंड"},
  {"word": "put", "pos": "V", "marathi": "पुट"},
  {"word": "home", "pos": "N", "marathi": "होम"},
  {"word": "read", "pos": "V", "marathi": "रीड"},
  {"word": "hand", "pos": "N", "marathi": "हँड"},
  {"word": "port", "pos": "N", "marathi": "पोर्ट"},
  {"word": "large", "pos": "ADJ", "marathi": "लार्ज"},
  {"word": "spell", "pos": "V", "marathi": "स्पेल"},
  {"word": "add", "pos": "V", "marathi": "ऍड"},
  {"word": "even", "pos": "ADV", "marathi": "ईवन"},
  {"word": "land", "pos": "N", "marathi": "लँड"},
  {"word": "here", "pos": "ADV", "marathi": "हियर"},
  {"word": "must", "pos": "MODAL", "marathi": "मस्ट"},
  {"word": "big", "pos": "ADJ", "marathi": "बिग"},
  {"word": "high", "pos": "ADJ", "marathi": "हाई"},
  {"word": "such", "pos": "DET", "marathi": "सच"},
  {"word": "follow", "pos": "V", "marathi": "फॉलो"},
  {"word": "act", "pos": "V", "marathi": "ऍक्ट"},
  {"word": "why", "pos": "ADV", "marathi": "वाई"},
  {"word": "ask", "pos": "V", "marathi": "आस्क"},
  {"word": "men", "pos": "N", "marathi": "मेन"},
  {"word": "change", "pos": "V", "marathi": "चेंज"},
  {"word": "went", "pos": "V", "marathi": "वेंट"},
  {"word": "light", "pos": "N", "marathi": "लाईट"},
  {"word": "kind", "pos": "N", "marathi": "काईंड"},
  {"word": "off", "pos": "PREP", "marathi": "ऑफ"},
  {"word": "need", "pos": "V", "marathi": "नीड"},
  {"word": "house", "pos": "N", "marathi": "हाउस"},
  {"word": "picture", "pos": "N", "marathi": "पिक्चर"},
  {"word": "try", "pos": "V", "marathi": "ट्राय"},
  {"word": "us", "pos": "PRON", "marathi": "अस"}
]
